.gitignore
README.rst
setup.py
docs/Makefile
docs/conf.py
docs/index.rst
docs/make.bat
docs/_themes/LICENSE
docs/_themes/README.rst
docs/_themes/flask_theme_support.py
docs/_themes/kr/layout.html
docs/_themes/kr/relations.html
docs/_themes/kr/theme.conf
docs/_themes/kr/static/flasky.css_t
docs/_themes/kr/static/small_flask.css
docs/_themes/kr_small/layout.html
docs/_themes/kr_small/theme.conf
docs/_themes/kr_small/static/flasky.css_t
katapayadi/__init__.py
katapayadi/core.py
katapayadi.egg-info/PKG-INFO
katapayadi.egg-info/SOURCES.txt
katapayadi.egg-info/dependency_links.txt
katapayadi.egg-info/not-zip-safe
katapayadi.egg-info/requires.txt
katapayadi.egg-info/top_level.txt
katapayadi/templates/katapayadi.html
tests/__init__.py
tests/katapayadi_test.py