Metadata-Version: 1.0
Name: katapayadi
Version: 0.2.0
Summary: Decode katapayadi number system
Home-page: http://silpa.org.in/Katapayadi
Author: Santhosh Thottingal
Author-email: santhosh.thottingal@gmail.com
License: LGPL-3.0
Platform: UNKNOWN
